odoo/addons/partner_title_order/README.rst
odoo/addons/partner_title_order/__init__.py
odoo/addons/partner_title_order/__manifest__.py
odoo/addons/partner_title_order/i18n/es.po
odoo/addons/partner_title_order/i18n/fr.po
odoo/addons/partner_title_order/i18n/it.po
odoo/addons/partner_title_order/i18n/partner_title_order.pot
odoo/addons/partner_title_order/models/__init__.py
odoo/addons/partner_title_order/models/res_partner_title.py
odoo/addons/partner_title_order/readme/CONTRIBUTORS.rst
odoo/addons/partner_title_order/readme/CREDITS.rst
odoo/addons/partner_title_order/readme/DESCRIPTION.rst
odoo/addons/partner_title_order/static/description/icon.png
odoo/addons/partner_title_order/static/description/index.html
odoo/addons/partner_title_order/tests/__init__.py
odoo/addons/partner_title_order/tests/test_partner_title.py
odoo/addons/partner_title_order/views/res_partner_title_views.xml
odoo14_addon_partner_title_order-14.0.1.0.1.dev12.dist-info/METADATA
odoo14_addon_partner_title_order-14.0.1.0.1.dev12.dist-info/WHEEL
odoo14_addon_partner_title_order-14.0.1.0.1.dev12.dist-info/top_level.txt
odoo14_addon_partner_title_order-14.0.1.0.1.dev12.dist-info/RECORD
